deckset_inline/__init__.py
deckset_inline/__version__.py
deckset_inline/inliner.py
deckset_inline-0.1.0.dist-info/LICENSE
deckset_inline-0.1.0.dist-info/METADATA
deckset_inline-0.1.0.dist-info/WHEEL
deckset_inline-0.1.0.dist-info/entry_points.txt
deckset_inline-0.1.0.dist-info/top_level.txt
deckset_inline-0.1.0.dist-info/RECORD
