Metadata-Version: 2.1
Name: deckset-inline
Version: 0.1.0
Summary: A tool to inline content in a Deckset Markdown file
Home-page: https://github.com/jdevera/deckset-inline
Author: Jacobo de Vera
Author-email: devel@jacobodevera.com
License: MIT
Platform: UNKNOWN
Classifier: Development Status :: 4 - Beta
Classifier: License :: OSI Approved :: MIT License
Classifier: Programming Language :: Python :: 3
Classifier: Programming Language :: Python :: 3.8
Classifier: Topic :: Text Processing :: Filters
Classifier: Topic :: Utilities
